LICENSE
README.md
setup.py
cloudmersive_spam_api_client/__init__.py
cloudmersive_spam_api_client/api_client.py
cloudmersive_spam_api_client/configuration.py
cloudmersive_spam_api_client/rest.py
cloudmersive_spam_api_client.egg-info/PKG-INFO
cloudmersive_spam_api_client.egg-info/SOURCES.txt
cloudmersive_spam_api_client.egg-info/dependency_links.txt
cloudmersive_spam_api_client.egg-info/requires.txt
cloudmersive_spam_api_client.egg-info/top_level.txt
cloudmersive_spam_api_client/api/__init__.py
cloudmersive_spam_api_client/api/spam_detection_api.py
cloudmersive_spam_api_client/models/__init__.py
cloudmersive_spam_api_client/models/spam_detection_advanced_form_field.py
cloudmersive_spam_api_client/models/spam_detection_advanced_form_submission_request.py
cloudmersive_spam_api_client/models/spam_detection_advanced_request.py
cloudmersive_spam_api_client/models/spam_detection_advanced_response.py
cloudmersive_spam_api_client/models/spam_detection_form_submission_advanced_response.py
cloudmersive_spam_api_client/models/spam_detection_request.py
cloudmersive_spam_api_client/models/spam_detection_response.py
test/__init__.py
test/test_spam_detection_advanced_form_field.py
test/test_spam_detection_advanced_form_submission_request.py
test/test_spam_detection_advanced_request.py
test/test_spam_detection_advanced_response.py
test/test_spam_detection_api.py
test/test_spam_detection_form_submission_advanced_response.py
test/test_spam_detection_request.py
test/test_spam_detection_response.py