Metadata-Version: 2.4
Name: cloudmersive_spam_api_client
Version: 3.0.4
Summary: spamapi
Home-page: https://cloudmersive.com/spam-detection-api
Author-email: 
Keywords: Swagger,spamapi
License-File: LICENSE
Requires-Dist: certifi>=2017.4.17
Requires-Dist: python-dateutil>=2.1
Requires-Dist: six>=1.10
Requires-Dist: urllib3>=1.23
Dynamic: description
Dynamic: description-content-type
Dynamic: home-page
Dynamic: keywords
Dynamic: license-file
Dynamic: requires-dist
Dynamic: summary
